diddiparser2/__init__.py
diddiparser2/__main__.py
diddiparser2/cli.py
diddiparser2/diddiscript_types.py
diddiparser2/messages.py
diddiparser2/parser.py
diddiparser2/editor/__init__.py
diddiparser2/editor/__main__.py
diddiparser2/editor/formatter.py
diddiparser2/editor/main.py
diddiparser2/lib/__init__.py
diddiparser2/lib/_builtin.py
diddiparser2/lib/fileio.py
diddiparser2/lib/math.py
diddiparser2/lib/simpleio.py
diddiparser2/lib/sqlite.py
diddiparser2/lib/subprocessing.py
diddiparser2-1.2.0.dist-info/LICENSE.txt
diddiparser2-1.2.0.dist-info/METADATA
diddiparser2-1.2.0.dist-info/WHEEL
diddiparser2-1.2.0.dist-info/entry_points.txt
diddiparser2-1.2.0.dist-info/top_level.txt
diddiparser2-1.2.0.dist-info/RECORD
