Metadata-Version: 2.1
Name: diddiparser2
Version: 1.2.0
Summary: The official DiddiScript parser.
Home-page: http://diddiparser2.readthedocs.io
Author: Diego Ramirez
Author-email: dr01191115@gmail.com
License: MIT License
Project-URL: Documentation, http://diddiparser2.readthedocs.io
Project-URL: Tracker, http://github.com/DiddiLeija/diddiparser2/issues
Project-URL: Source, http://github.com/DiddiLeija/diddiparser2
Keywords: diddiscript python parser
Platform: UNKNOWN
Classifier: Development Status :: 5 - Production/Stable
Classifier: Intended Audience :: Developers
Classifier: Natural Language :: English
Classifier: Programming Language :: Python :: 3
Classifier: Programming Language :: Python :: 3 :: Only
Classifier: Programming Language :: Python :: 3.7
Classifier: Programming Language :: Python :: 3.8
Classifier: Programming Language :: Python :: 3.9
Classifier: Programming Language :: Python :: 3.10
Classifier: License :: OSI Approved :: MIT License
Classifier: Operating System :: OS Independent
Classifier: Operating System :: POSIX
Classifier: Operating System :: MacOS
Classifier: Operating System :: MacOS :: MacOS X
Classifier: Operating System :: Microsoft
Classifier: Operating System :: Microsoft :: Windows
Classifier: Operating System :: Unix
Classifier: Topic :: Software Development
Classifier: Topic :: Software Development :: Compilers
Classifier: Topic :: Software Development :: Interpreters
Classifier: Topic :: Software Development :: Libraries
Requires-Python: >=3.7
License-File: LICENSE.txt
Requires-Dist: colorama (>=0.4.0)
